xvideos/__init__.py
xvideos/reader.py
xvideos/utils/__init__.py
xvideos/utils/help_functions.py
xvideos-0.3.dist-info/LICENSE
xvideos-0.3.dist-info/METADATA
xvideos-0.3.dist-info/WHEEL
xvideos-0.3.dist-info/top_level.txt
xvideos-0.3.dist-info/RECORD
