Metadata-Version: 2.1
Name: xvideos
Version: 0.3
Summary: UNKNOWN
Home-page: https://github.com/tam2511/xvideos
Author: Alexander Timofeev
Author-email: tam2511@mail.ru
License: UNKNOWN
Platform: UNKNOWN
Classifier: Programming Language :: Python :: 3
Classifier: License :: OSI Approved :: MIT License
Classifier: Operating System :: OS Independent
Requires-Python: >=3.6
License-File: LICENSE
Requires-Dist: opencv-python
